async_stagger/__init__.py
async_stagger/aitertools.py
async_stagger/conftest.py
async_stagger/constants.py
async_stagger/debug.py
async_stagger/exceptions.py
async_stagger/happy_eyeballs.py
async_stagger/resolvers.py
async_stagger/stagger.py
async_stagger/test_aitertools.py
async_stagger/test_happy_eyeballs.py
async_stagger/test_resolvers.py
async_stagger/test_stagger.py
async_stagger/typing.py
async_stagger-0.4.1.dist-info/LICENSE.txt
async_stagger-0.4.1.dist-info/METADATA
async_stagger-0.4.1.dist-info/WHEEL
async_stagger-0.4.1.dist-info/top_level.txt
async_stagger-0.4.1.dist-info/RECORD
