Metadata-Version: 2.2
Name: async_stagger
Version: 0.4.1
Summary: Happy eyeballs and underlying scheduling algorithm in asyncio
Author-email: twisteroid ambassador <twisteroid.ambassador@gmail.com>
Project-URL: Homepage, https://github.com/twisteroidambassador/async_stagger
Project-URL: Documentation, https://async-stagger.readthedocs.io
Keywords: happy-eyeballs,dual-stack,tcp
Classifier: Development Status :: 3 - Alpha
Classifier: Intended Audience :: Developers
Classifier: Operating System :: OS Independent
Classifier: Framework :: AsyncIO
Classifier: License :: OSI Approved :: MIT License
Classifier: Programming Language :: Python :: 3
Classifier: Programming Language :: Python :: 3.11
Classifier: Programming Language :: Python :: 3.12
Classifier: Programming Language :: Python :: 3.13
Requires-Python: >=3.11
License-File: LICENSE.txt
Provides-Extra: test
Requires-Dist: pytest; extra == "test"
Requires-Dist: pytest-asyncio; extra == "test"
